hatch_datavolo_nar/__about__.py
hatch_datavolo_nar/__init__.py
hatch_datavolo_nar/builder.py
hatch_datavolo_nar/hooks.py
hatch_datavolo_nar-1.0.1.dist-info/METADATA
hatch_datavolo_nar-1.0.1.dist-info/WHEEL
hatch_datavolo_nar-1.0.1.dist-info/entry_points.txt
hatch_datavolo_nar-1.0.1.dist-info/licenses/LICENSE
hatch_datavolo_nar-1.0.1.dist-info/RECORD
