Metadata-Version: 2.3
Name: hatch-datavolo-nar
Version: 1.0.1
Summary: Hatch plugin for building Apache NiFi NAR bundles
Project-URL: Issues, https://github.com/datavolo-io/hatch-datavolo-nar/issues
Project-URL: Source, https://github.com/datavolo-io/hatch-datavolo-nar
Author-email: Datavolo Developers <dev@datavolo.io>
Maintainer-email: Datavolo Developers <dev@datavolo.io>
License:                                  Apache License
License-File: LICENSE
Keywords: datavolo,hatch,nar,nifi
Classifier: Development Status :: 5 - Production/Stable
Classifier: Framework :: Hatch
Classifier: Intended Audience :: Developers
Classifier: License :: OSI Approved :: Apache Software License
Classifier: Programming Language :: Python
Classifier: Programming Language :: Python :: 3.11
Classifier: Programming Language :: Python :: 3.12
Requires-Python: >=3.11
Requires-Dist: hatchling
